pai_agent_sdk/__init__.py
pai_agent_sdk/_config.py
pai_agent_sdk/_logger.py
pai_agent_sdk/events.py
pai_agent_sdk/mcp.py
pai_agent_sdk/presets.py
pai_agent_sdk/usage.py
pai_agent_sdk/utils.py
pai_agent_sdk/agents/__init__.py
pai_agent_sdk/agents/compact.py
pai_agent_sdk/agents/guards.py
pai_agent_sdk/agents/image_understanding.py
pai_agent_sdk/agents/main.py
pai_agent_sdk/agents/video_understanding.py
pai_agent_sdk/agents/models/__init__.py
pai_agent_sdk/agents/models/gateway.py
pai_agent_sdk/agents/models/utils.py
pai_agent_sdk/agents/prompts/compact.md
pai_agent_sdk/agents/prompts/image_understanding.md
pai_agent_sdk/agents/prompts/main.md
pai_agent_sdk/agents/prompts/video_understanding.md
pai_agent_sdk/context/__init__.py
pai_agent_sdk/context/agent.py
pai_agent_sdk/context/bus.py
pai_agent_sdk/context/tasks.py
pai_agent_sdk/environment/__init__.py
pai_agent_sdk/environment/docker.py
pai_agent_sdk/environment/local.py
pai_agent_sdk/filters/__init__.py
pai_agent_sdk/filters/auto_load_files.py
pai_agent_sdk/filters/bus_message.py
pai_agent_sdk/filters/capability.py
pai_agent_sdk/filters/environment_instructions.py
pai_agent_sdk/filters/handoff.py
pai_agent_sdk/filters/image.py
pai_agent_sdk/filters/model_swtich.py
pai_agent_sdk/filters/runtime_instructions.py
pai_agent_sdk/filters/system_prompt.py
pai_agent_sdk/filters/tool_args.py
pai_agent_sdk/sandbox/__init__.py
pai_agent_sdk/sandbox/browser/__init__.py
pai_agent_sdk/sandbox/browser/base.py
pai_agent_sdk/sandbox/browser/docker_.py
pai_agent_sdk/stream/__init__.py
pai_agent_sdk/subagents/__init__.py
pai_agent_sdk/subagents/config.py
pai_agent_sdk/subagents/factory.py
pai_agent_sdk/subagents/presets/code-reviewer.md
pai_agent_sdk/subagents/presets/debugger.md
pai_agent_sdk/subagents/presets/executor.md
pai_agent_sdk/subagents/presets/explorer.md
pai_agent_sdk/subagents/presets/searcher.md
pai_agent_sdk/toolsets/__init__.py
pai_agent_sdk/toolsets/base.py
pai_agent_sdk/toolsets/browser_use/__init__.py
pai_agent_sdk-0.13.0.dist-info/METADATA
pai_agent_sdk-0.13.0.dist-info/WHEEL
pai_agent_sdk-0.13.0.dist-info/licenses/LICENSE
pai_agent_sdk-0.13.0.dist-info/RECORD
