Metadata-Version: 2.4
Name: pai-agent-sdk
Version: 0.13.0
Summary: Application framework for building AI agents with Pydantic AI - environment abstractions, session management, and hierarchical agent patterns
Project-URL: Repository, https://github.com/youware-labs/pai-agent-sdk
Author-email: youware <lab@youware.com>
License-File: LICENSE
Keywords: python
Classifier: Intended Audience :: Developers
Classifier: Programming Language :: Python
Classifier: Programming Language :: Python :: 3
Classifier: Programming Language :: Python :: 3.11
Classifier: Programming Language :: Python :: 3.12
Classifier: Programming Language :: Python :: 3.13
Classifier: Topic :: Software Development :: Libraries :: Python Modules
Requires-Python: <3.14,>=3.11
Requires-Dist: agent-environment==0.4.0
Requires-Dist: anyio>=4.12.0
Requires-Dist: cdp-use<2.0.0,>=1.4.4
Requires-Dist: httpx>=0.28.1
Requires-Dist: jinja2>=3.0.0
Requires-Dist: pathspec>=0.12.0
Requires-Dist: pillow>=10.0.0
Requires-Dist: pydantic-ai-slim>=1.42.0
Requires-Dist: pydantic-settings>=2.0.0
Requires-Dist: pydantic>=2.12.5
Requires-Dist: pyyaml>=6.0.0
Requires-Dist: tenacity>=9.0.0
Requires-Dist: typing-extensions>=4.15.0
Provides-Extra: all
Requires-Dist: docker>=7.0.0; extra == 'all'
Requires-Dist: firecrawl-py>=4.0.0; extra == 'all'
Requires-Dist: markitdown[all]>=0.1.2; extra == 'all'
Requires-Dist: pydantic-ai; extra == 'all'
Requires-Dist: pymupdf-layout>=1.26.6; extra == 'all'
Requires-Dist: pymupdf4llm>=0.2.8; extra == 'all'
Requires-Dist: pymupdf>=1.26.6; extra == 'all'
Requires-Dist: python-dotenv; extra == 'all'
Requires-Dist: tavily-python>=0.7.0; extra == 'all'
Provides-Extra: docker
Requires-Dist: docker>=7.0.0; extra == 'docker'
Provides-Extra: document
Requires-Dist: markitdown[all]>=0.1.2; extra == 'document'
Requires-Dist: pymupdf-layout>=1.26.6; extra == 'document'
Requires-Dist: pymupdf4llm>=0.2.8; extra == 'document'
Requires-Dist: pymupdf>=1.26.6; extra == 'document'
Provides-Extra: examples
Requires-Dist: pydantic-ai; extra == 'examples'
Requires-Dist: python-dotenv; extra == 'examples'
Provides-Extra: web
Requires-Dist: firecrawl-py>=4.0.0; extra == 'web'
Requires-Dist: markitdown[all]>=0.1.2; extra == 'web'
Requires-Dist: tavily-python>=0.7.0; extra == 'web'
